versioningit/__init__.py
versioningit/__main__.py
versioningit/basics.py
versioningit/cmdclass.py
versioningit/config.py
versioningit/core.py
versioningit/errors.py
versioningit/get_cmdclasses.py
versioningit/git.py
versioningit/hatch.py
versioningit/hg.py
versioningit/hook.py
versioningit/logging.py
versioningit/methods.py
versioningit/next_version.py
versioningit/onbuild.py
versioningit/py.typed
versioningit/util.py
versioningit-3.2.0.dist-info/METADATA
versioningit-3.2.0.dist-info/WHEEL
versioningit-3.2.0.dist-info/entry_points.txt
versioningit-3.2.0.dist-info/licenses/LICENSE
versioningit-3.2.0.dist-info/RECORD
