Metadata-Version: 2.4
Name: versioningit
Version: 3.2.0
Summary: Versioning It with your Version In Git
Project-URL: Source Code, https://github.com/jwodder/versioningit
Project-URL: Bug Tracker, https://github.com/jwodder/versioningit/issues
Project-URL: Documentation, https://versioningit.readthedocs.io
Author-email: John Thorvald Wodder II <versioningit@varonathe.org>
License-Expression: MIT
License-File: LICENSE
Keywords: Git,Mercurial,VCS,packaging,version
Classifier: Development Status :: 5 - Production/Stable
Classifier: Framework :: Hatch
Classifier: Framework :: Setuptools Plugin
Classifier: Intended Audience :: Developers
Classifier: Programming Language :: Python :: 3
Classifier: Programming Language :: Python :: 3 :: Only
Classifier: Programming Language :: Python :: 3.8
Classifier: Programming Language :: Python :: 3.9
Classifier: Programming Language :: Python :: 3.10
Classifier: Programming Language :: Python :: 3.11
Classifier: Programming Language :: Python :: 3.12
Classifier: Programming Language :: Python :: 3.13
Classifier: Programming Language :: Python :: Implementation :: CPython
Classifier: Programming Language :: Python :: Implementation :: PyPy
Classifier: Topic :: Software Development :: Build Tools
Classifier: Topic :: Software Development :: Version Control
Classifier: Topic :: Software Development :: Version Control :: Git
Classifier: Topic :: Software Development :: Version Control :: Mercurial
Classifier: Typing :: Typed
Requires-Python: >=3.8
Requires-Dist: importlib-metadata>=3.6; python_version < '3.10'
Requires-Dist: packaging>=17.1
Requires-Dist: tomli<3.0,>=1.2; python_version < '3.11'
